ShareImage/__init__.py
ShareImage-2.2.0.dist-info/LICENSE
ShareImage-2.2.0.dist-info/METADATA
ShareImage-2.2.0.dist-info/WHEEL
ShareImage-2.2.0.dist-info/top_level.txt
ShareImage-2.2.0.dist-info/RECORD
