Metadata-Version: 2.1
Name: ShareImage
Version: 2.2.0
Summary: A Python Library to Generate Dynamic Share Images. Powered by Cloudinary.
Home-page: https://github.com/Zype-Z/ShareImage
Author: Zype Inc.
Author-email: info@zype.cf
Maintainer: Rajdeep Malakar
Maintainer-email: Rajdeep@zype.cf
License: UNKNOWN
Platform: UNKNOWN
Classifier: Programming Language :: Python :: 3
Classifier: License :: OSI Approved :: MIT License
Classifier: Operating System :: OS Independent
Requires-Python: >=3.6
